jb_qt/__init__.py
jb_qt/common/__init__.py
jb_qt/common/consts.py
jb_qt/common/qt_utils.py
jb_qt/dialogs/__init__.py
jb_qt/dialogs/file_dialog.py
jb_qt/dialogs/input_form.py
jb_qt/dialogs/text_preview.py
jb_qt/models/__init__.py
jb_qt/models/chip_button.py
jb_qt/models/chips.py
jb_qt/view_icons.py
jb_qt/widgets/__init__.py
jb_qt/widgets/chip_button.py
jb_qt/widgets/chips.py
jb_qt/widgets/multiselect.py
jb_qt/widgets/simple.py
jb_qt/widgets/toast.py
jb_qt/widgets/widget_utils.py
jb_qt-0.1.21.dist-info/METADATA
jb_qt-0.1.21.dist-info/WHEEL
jb_qt-0.1.21.dist-info/RECORD
